neteria/__init__.py
neteria/client.py
neteria/core.py
neteria/encryption.py
neteria/server.py
neteria/tools.py
neteria-1.0.2.dist-info/DESCRIPTION.rst
neteria-1.0.2.dist-info/METADATA
neteria-1.0.2.dist-info/RECORD
neteria-1.0.2.dist-info/WHEEL
neteria-1.0.2.dist-info/metadata.json
neteria-1.0.2.dist-info/top_level.txt
